steemtools/__init__.py
steemtools/base.py
steemtools/blockchain.py
steemtools/experimental.py
steemtools/helpers.py
steemtools/markets.py
steemtools/node.py
steemtools-1.4.2.dist-info/DESCRIPTION.rst
steemtools-1.4.2.dist-info/METADATA
steemtools-1.4.2.dist-info/RECORD
steemtools-1.4.2.dist-info/WHEEL
steemtools-1.4.2.dist-info/metadata.json
steemtools-1.4.2.dist-info/top_level.txt
