Metadata-Version: 2.0
Name: steemtools
Version: 1.4.2
Summary: Python Utilities for parsing STEEM blockchain
Home-page: https://github.com/Netherdrake/steemtools
Author: @furion
Author-email: _@furion.me
License: MIT
Keywords: steem steemit
Platform: UNKNOWN
Classifier: Development Status :: 3 - Alpha
Classifier: Intended Audience :: Developers
Classifier: License :: OSI Approved :: MIT License
Classifier: Programming Language :: Python :: 3.5
Requires-Dist: funcy
Requires-Dist: grequests
Requires-Dist: numpy
Requires-Dist: python-dateutil
Requires-Dist: requests
Requires-Dist: steem-piston
Requires-Dist: tqdm
Requires-Dist: werkzeug
Provides-Extra: dev
Requires-Dist: check-manifest; extra == 'dev'
Requires-Dist: matplotlib; extra == 'dev'
Requires-Dist: pandas; extra == 'dev'
Requires-Dist: pymongo; extra == 'dev'
Provides-Extra: test
Requires-Dist: coverage; extra == 'test'
